papermill/__init__.py
papermill/__main__.py
papermill/abs.py
papermill/adl.py
papermill/cli.py
papermill/clientwrap.py
papermill/engines.py
papermill/exceptions.py
papermill/execute.py
papermill/inspection.py
papermill/iorw.py
papermill/log.py
papermill/models.py
papermill/parameterize.py
papermill/s3.py
papermill/translators.py
papermill/utils.py
papermill/version.py
papermill-2.5.0.dist-info/LICENSE
papermill-2.5.0.dist-info/METADATA
papermill-2.5.0.dist-info/WHEEL
papermill-2.5.0.dist-info/entry_points.txt
papermill-2.5.0.dist-info/top_level.txt
papermill-2.5.0.dist-info/RECORD
