Metadata-Version: 2.1
Name: papermill
Version: 2.5.0
Summary: Parameterize and run Jupyter and nteract Notebooks
Home-page: https://github.com/nteract/papermill
Author: nteract contributors
Author-email: nteract@googlegroups.com
License: BSD
Project-URL: Documentation, https://papermill.readthedocs.io
Project-URL: Funding, https://nteract.io
Project-URL: Source, https://github.com/nteract/papermill/
Project-URL: Tracker, https://github.com/nteract/papermill/issues
Keywords: jupyter mapreduce nteract pipeline notebook
Classifier: Intended Audience :: Developers
Classifier: Intended Audience :: System Administrators
Classifier: Intended Audience :: Science/Research
Classifier: License :: OSI Approved :: BSD License
Classifier: Programming Language :: Python
Classifier: Programming Language :: Python :: 3
Classifier: Programming Language :: Python :: 3.8
Classifier: Programming Language :: Python :: 3.9
Classifier: Programming Language :: Python :: 3.10
Classifier: Programming Language :: Python :: 3.11
Classifier: Programming Language :: Python :: 3.12
Requires-Python: >=3.8
License-File: LICENSE
Requires-Dist: click
Requires-Dist: pyyaml
Requires-Dist: nbformat>=5.1.2
Requires-Dist: nbclient>=0.2.0
Requires-Dist: tqdm>=4.32.2
Requires-Dist: requests
Requires-Dist: entrypoints
Requires-Dist: tenacity>=5.0.2
Requires-Dist: aiohttp==3.9.0b0; python_version == "3.12"
Provides-Extra: test
Requires-Dist: boto3; extra == "test"
Requires-Dist: botocore; extra == "test"
Requires-Dist: codecov; extra == "test"
Requires-Dist: coverage; extra == "test"
Requires-Dist: google_compute_engine; extra == "test"
Requires-Dist: ipython>=5.0; extra == "test"
Requires-Dist: ipywidgets; extra == "test"
Requires-Dist: notebook; extra == "test"
Requires-Dist: moto; extra == "test"
Requires-Dist: pytest>=4.1; extra == "test"
Requires-Dist: pytest-cov>=2.6.1; extra == "test"
Requires-Dist: pytest-mock>=1.10; extra == "test"
Requires-Dist: pytest-env>=0.6.2; extra == "test"
Requires-Dist: requests>=2.21.0; extra == "test"
Requires-Dist: check-manifest; extra == "test"
Requires-Dist: attrs>=17.4.0; extra == "test"
Requires-Dist: pre-commit; extra == "test"
Requires-Dist: flake8; extra == "test"
Requires-Dist: tox; extra == "test"
Requires-Dist: bumpversion; extra == "test"
Requires-Dist: recommonmark; extra == "test"
Requires-Dist: pip>=18.1; extra == "test"
Requires-Dist: wheel>=0.31.0; extra == "test"
Requires-Dist: setuptools>=38.6.0; extra == "test"
Requires-Dist: twine>=1.11.0; extra == "test"
Requires-Dist: boto3; extra == "test"
Requires-Dist: azure-datalake-store>=0.0.30; extra == "test"
Requires-Dist: azure-storage-blob>=12.1.0; extra == "test"
Requires-Dist: requests>=2.21.0; extra == "test"
Requires-Dist: azure-identity>=1.3.1; extra == "test"
Requires-Dist: gcsfs>=0.2.0; extra == "test"
Requires-Dist: black>=19.3b0; extra == "test"
Provides-Extra: dev
Requires-Dist: boto3; extra == "dev"
Requires-Dist: botocore; extra == "dev"
Requires-Dist: codecov; extra == "dev"
Requires-Dist: coverage; extra == "dev"
Requires-Dist: google_compute_engine; extra == "dev"
Requires-Dist: ipython>=5.0; extra == "dev"
Requires-Dist: ipywidgets; extra == "dev"
Requires-Dist: notebook; extra == "dev"
Requires-Dist: moto; extra == "dev"
Requires-Dist: pytest>=4.1; extra == "dev"
Requires-Dist: pytest-cov>=2.6.1; extra == "dev"
Requires-Dist: pytest-mock>=1.10; extra == "dev"
Requires-Dist: pytest-env>=0.6.2; extra == "dev"
Requires-Dist: requests>=2.21.0; extra == "dev"
Requires-Dist: check-manifest; extra == "dev"
Requires-Dist: attrs>=17.4.0; extra == "dev"
Requires-Dist: pre-commit; extra == "dev"
Requires-Dist: flake8; extra == "dev"
Requires-Dist: tox; extra == "dev"
Requires-Dist: bumpversion; extra == "dev"
Requires-Dist: recommonmark; extra == "dev"
Requires-Dist: pip>=18.1; extra == "dev"
Requires-Dist: wheel>=0.31.0; extra == "dev"
Requires-Dist: setuptools>=38.6.0; extra == "dev"
Requires-Dist: twine>=1.11.0; extra == "dev"
Requires-Dist: boto3; extra == "dev"
Requires-Dist: azure-datalake-store>=0.0.30; extra == "dev"
Requires-Dist: azure-storage-blob>=12.1.0; extra == "dev"
Requires-Dist: requests>=2.21.0; extra == "dev"
Requires-Dist: azure-identity>=1.3.1; extra == "dev"
Requires-Dist: gcsfs>=0.2.0; extra == "dev"
Requires-Dist: black>=19.3b0; extra == "dev"
Provides-Extra: all
Requires-Dist: boto3; extra == "all"
Requires-Dist: azure-datalake-store>=0.0.30; extra == "all"
Requires-Dist: azure-storage-blob>=12.1.0; extra == "all"
Requires-Dist: requests>=2.21.0; extra == "all"
Requires-Dist: azure-identity>=1.3.1; extra == "all"
Requires-Dist: gcsfs>=0.2.0; extra == "all"
Requires-Dist: pyarrow>=2.0; extra == "all"
Requires-Dist: PyGithub>=1.55; extra == "all"
Requires-Dist: black>=19.3b0; extra == "all"
Provides-Extra: s3
Requires-Dist: boto3; extra == "s3"
Provides-Extra: azure
Requires-Dist: azure-datalake-store>=0.0.30; extra == "azure"
Requires-Dist: azure-storage-blob>=12.1.0; extra == "azure"
Requires-Dist: requests>=2.21.0; extra == "azure"
Requires-Dist: azure-identity>=1.3.1; extra == "azure"
Provides-Extra: gcs
Requires-Dist: gcsfs>=0.2.0; extra == "gcs"
Provides-Extra: hdfs
Requires-Dist: pyarrow>=2.0; extra == "hdfs"
Provides-Extra: github
Requires-Dist: PyGithub>=1.55; extra == "github"
Provides-Extra: black
Requires-Dist: black>=19.3b0; extra == "black"
Provides-Extra: docs
Requires-Dist: boto3; extra == "docs"
Requires-Dist: azure-datalake-store>=0.0.30; extra == "docs"
Requires-Dist: azure-storage-blob>=12.1.0; extra == "docs"
Requires-Dist: requests>=2.21.0; extra == "docs"
Requires-Dist: azure-identity>=1.3.1; extra == "docs"
Requires-Dist: gcsfs>=0.2.0; extra == "docs"
Requires-Dist: pyarrow>=2.0; extra == "docs"
Requires-Dist: PyGithub>=1.55; extra == "docs"
Requires-Dist: black>=19.3b0; extra == "docs"
Requires-Dist: Sphinx>=3.5.4; extra == "docs"
Requires-Dist: furo>=2021.4.11b34; extra == "docs"
Requires-Dist: myst-parser>=0.13.7; extra == "docs"
Requires-Dist: moto>=2.0.5; extra == "docs"
Requires-Dist: sphinx-copybutton>=0.3.1; extra == "docs"
